fcgdctools/__init__.py
fcgdctools/fc_loadfiles.py
fcgdctools/gdc_uuidresolver.py
fcgdctools-0.1.8.dist-info/DESCRIPTION.rst
fcgdctools-0.1.8.dist-info/METADATA
fcgdctools-0.1.8.dist-info/RECORD
fcgdctools-0.1.8.dist-info/WHEEL
fcgdctools-0.1.8.dist-info/entry_points.txt
fcgdctools-0.1.8.dist-info/metadata.json
fcgdctools-0.1.8.dist-info/top_level.txt
