Metadata-Version: 2.0
Name: fcgdctools
Version: 0.1.8
Summary: Utilities for integrating FireCloud and GDC
Home-page: https://github.com/broadinstitute/fcgdctools
Author: Chet Birger
Author-email: birger@broadinstitute.org
License: UNKNOWN
Platform: UNKNOWN
Classifier: Programming Language :: Python :: 3
Classifier: Intended Audience :: Science/Research
Classifier: Topic :: Scientific/Engineering :: Bio-Informatics
Classifier: License :: OSI Approved :: BSD License
Classifier: Operating System :: OS Independent
Classifier: Development Status :: 2 - Pre-Alpha
Requires-Dist: requests
